promptflow/azure/__init__.py
promptflow/azure/_cli/__init__.py
promptflow/azure/_cli/_connection.py
promptflow/azure/_cli/_flow.py
promptflow/azure/_cli/_run.py
promptflow/azure/_cli/_user_agent.py
promptflow/azure/_cli/_utils.py
promptflow/azure/_cli/entry.py
promptflow/azure/_constants/__init__.py
promptflow/azure/_constants/_component.py
promptflow/azure/_constants/_flow.py
promptflow/azure/_constants/_trace.py
promptflow/azure/_dependencies/_pf_evals.py
promptflow/azure/_entities/__init__.py
promptflow/azure/_entities/_flow.py
promptflow/azure/_entities/_trace.py
promptflow/azure/_entities/_workspace_connection_spec.py
promptflow/azure/_load_functions.py
promptflow/azure/_ml/__init__.py
promptflow/azure/_pf_client.py
promptflow/azure/_restclient/README.md
promptflow/azure/_restclient/__init__.py
promptflow/azure/_restclient/flow/__init__.py
promptflow/azure/_restclient/flow/_azure_machine_learning_designer_service_client.py
promptflow/azure/_restclient/flow/_configuration.py
promptflow/azure/_restclient/flow/_patch.py
promptflow/azure/_restclient/flow/_vendor.py
promptflow/azure/_restclient/flow/aio/__init__.py
promptflow/azure/_restclient/flow/aio/_azure_machine_learning_designer_service_client.py
promptflow/azure/_restclient/flow/aio/_configuration.py
promptflow/azure/_restclient/flow/aio/_patch.py
promptflow/azure/_restclient/flow/aio/operations/__init__.py
promptflow/azure/_restclient/flow/aio/operations/_bulk_runs_operations.py
promptflow/azure/_restclient/flow/aio/operations/_connection_operations.py
promptflow/azure/_restclient/flow/aio/operations/_connections_operations.py
promptflow/azure/_restclient/flow/aio/operations/_experiment_templates_operations.py
promptflow/azure/_restclient/flow/aio/operations/_experiment_templates_provider_operations.py
promptflow/azure/_restclient/flow/aio/operations/_experiments_operations.py
promptflow/azure/_restclient/flow/aio/operations/_experiments_provider_operations.py
promptflow_azure-1.18.2.dist-info/METADATA
promptflow_azure-1.18.2.dist-info/WHEEL
promptflow_azure-1.18.2.dist-info/entry_points.txt
promptflow_azure-1.18.2.dist-info/RECORD
