Metadata-Version: 2.4
Name: promptflow-azure
Version: 1.18.2
Summary: Prompt flow azure
License: MIT
Keywords: azure
Author: Microsoft Corporation
Author-email: aml-pt-eng@microsoft.com
Requires-Python: >=3.9, !=2.7.*, !=3.0.*, !=3.1.*, !=3.2.*, !=3.3.*, !=3.4.*, !=3.5.*, !=3.6.*, !=3.7.*, !=3.8.*, !=3.14.*
Classifier: License :: OSI Approved :: MIT License
Classifier: Operating System :: OS Independent
Classifier: Programming Language :: Python
Classifier: Programming Language :: Python :: 3
Classifier: Programming Language :: Python :: 3.9
Classifier: Programming Language :: Python :: 3.10
Classifier: Programming Language :: Python :: 3.11
Classifier: Programming Language :: Python :: 3.12
Classifier: Programming Language :: Python :: 3.13
Classifier: Programming Language :: Python :: 3 :: Only
Requires-Dist: azure-ai-ml (>=1.14.0,<2.0.0)
Requires-Dist: azure-core (>=1.26.4,<2.0.0)
Requires-Dist: azure-cosmos (>=4.5.1,<5.0.0)
Requires-Dist: azure-identity (>=1.12.0,<2.0.0)
Requires-Dist: azure-storage-blob[aio] (>=12.17.0,<13.0.0)
Requires-Dist: promptflow-devkit (>=1.18.2,<2.0.0)
Requires-Dist: pyjwt (>=2.4.0,<3.0.0)
Project-URL: Bug Reports, https://github.com/microsoft/promptflow/issues
Project-URL: Homepage, https://microsoft.github.io/promptflow/
Project-URL: Repository, https://github.com/microsoft/promptflow
